skyplan/__init__.py
skyplan/examples.py
skyplan/skyplan.py
skyplan-0.1.0.dist-info/LICENSE
skyplan-0.1.0.dist-info/METADATA
skyplan-0.1.0.dist-info/WHEEL
skyplan-0.1.0.dist-info/top_level.txt
skyplan-0.1.0.dist-info/RECORD
