Metadata-Version: 2.1
Name: skyplan
Version: 0.1.0
Summary: Python package skyplan
Home-page: https://github.com/erdogant/skyplan
Download-URL: https://github.com/erdogant/skyplan/archive/0.1.0.tar.gz
Author: Erdogan Taskesen
Author-email: erdogant@gmail.com
Classifier: Programming Language :: Python :: 3
Classifier: License :: OSI Approved :: MIT License
Classifier: Operating System :: OS Independent
Requires-Python: >=3
License-File: LICENSE
